MANIFEST.in
README.rst
VERSION
setup.py
hitchelasticsearch/__init__.py
hitchelasticsearch/elastic_package.py
hitchelasticsearch/elastic_service.py
hitchelasticsearch.egg-info/PKG-INFO
hitchelasticsearch.egg-info/SOURCES.txt
hitchelasticsearch.egg-info/dependency_links.txt
hitchelasticsearch.egg-info/not-zip-safe
hitchelasticsearch.egg-info/requires.txt
hitchelasticsearch.egg-info/top_level.txt